slack_notifier/__init__.py
slack_notifier/notifier.py
aws_lambda_slack_notifier-0.1.0.dist-info/LICENSE.txt
aws_lambda_slack_notifier-0.1.0.dist-info/METADATA
aws_lambda_slack_notifier-0.1.0.dist-info/WHEEL
aws_lambda_slack_notifier-0.1.0.dist-info/top_level.txt
aws_lambda_slack_notifier-0.1.0.dist-info/RECORD
